orthax/__init__.py
orthax/_general.py
orthax/_version.py
orthax/chebyshev.py
orthax/hermite.py
orthax/hermite_e.py
orthax/laguerre.py
orthax/legendre.py
orthax/polynomial.py
orthax/polyutils.py
orthax/recurrence.py
orthax-0.2.6.dist-info/licenses/LICENSE
orthax-0.2.6.dist-info/METADATA
orthax-0.2.6.dist-info/WHEEL
orthax-0.2.6.dist-info/top_level.txt
orthax-0.2.6.dist-info/RECORD
