Metadata-Version: 2.4
Name: orthax
Version: 0.2.6
Summary: Orthogonal polynomials with JAX
Home-page: https://github.com/f0uriest/orthax
Author: Rory Conlin
Author-email: wconlin@princeton.edu
License: MIT
Project-URL: Issues Tracker, https://github.com/f0uriest/orthax/issues
Project-URL: Contributing, https://github.com/f0uriest/orthax/blob/master/CONTRIBUTING.rst
Project-URL: Source Code, https://github.com/f0uriest/orthax/
Project-URL: Documentation, https://orthax.readthedocs.io/
Keywords: polynomial orthogonal hermite laguerre legendre chebyshev
Classifier: Development Status :: 3 - Alpha
Classifier: Intended Audience :: Science/Research
Classifier: License :: OSI Approved :: MIT License
Classifier: Natural Language :: English
Classifier: Programming Language :: Python :: 3
Classifier: Programming Language :: Python :: 3.10
Classifier: Programming Language :: Python :: 3.11
Classifier: Programming Language :: Python :: 3.12
Classifier: Programming Language :: Python :: 3.13
Classifier: Topic :: Scientific/Engineering
Classifier: Topic :: Scientific/Engineering :: Mathematics
Requires-Python: >=3.10
License-File: LICENSE
Requires-Dist: equinox<0.14,>=0.11.0
Requires-Dist: jax<0.9,>=0.4.36
Requires-Dist: numpy<2.4,>=1.20.0
Dynamic: author
Dynamic: author-email
Dynamic: classifier
Dynamic: description
Dynamic: description-content-type
Dynamic: home-page
Dynamic: keywords
Dynamic: license
Dynamic: license-file
Dynamic: project-url
Dynamic: requires-dist
Dynamic: requires-python
Dynamic: summary
